cronrepo/__init__.py
cronrepo/__main__.py
cronrepo-0.3.4.dist-info/LICENSE
cronrepo-0.3.4.dist-info/METADATA
cronrepo-0.3.4.dist-info/WHEEL
cronrepo-0.3.4.dist-info/entry_points.txt
cronrepo-0.3.4.dist-info/top_level.txt
cronrepo-0.3.4.dist-info/RECORD
