Metadata-Version: 2.1
Name: cronrepo
Version: 0.3.4
Summary: Maintain a set of cron jobs in your code repository
Home-page: https://github.com/isaacto/cronrepo
Author: Isaac To
Author-email: isaac.to@gmail.com
Classifier: Development Status :: 4 - Beta
Classifier: Programming Language :: Python :: 3
Classifier: Topic :: Software Development :: Libraries
Classifier: License :: OSI Approved :: MIT License
Classifier: Operating System :: POSIX :: Linux
License-File: LICENSE
Requires-Dist: calf
Requires-Dist: croniter
